gitignore.py
auto_gitignore-1.0.0.dist-info/LICENSE
auto_gitignore-1.0.0.dist-info/METADATA
auto_gitignore-1.0.0.dist-info/WHEEL
auto_gitignore-1.0.0.dist-info/entry_points.txt
auto_gitignore-1.0.0.dist-info/top_level.txt
auto_gitignore-1.0.0.dist-info/RECORD
