Metadata-Version: 2.1
Name: auto-gitignore
Version: 1.0.0
Summary: Create gitignore template with autocompletion.
Home-page: https://github.com/Mux-Mastermann/gitignore
Author: Jan Knorr
Author-email: jan.hhc+dev@gmail.com
License: MIT
Platform: UNKNOWN
Requires-Dist: requests
Requires-Dist: prompt-toolkit
